napari_matplotlib/__init__.py
napari_matplotlib/_version.py
napari_matplotlib/base.py
napari_matplotlib/features.py
napari_matplotlib/histogram.py
napari_matplotlib/napari.yaml
napari_matplotlib/scatter.py
napari_matplotlib/slice.py
napari_matplotlib/util.py
napari_matplotlib/icons/black/Back.png
napari_matplotlib/icons/black/Customize.png
napari_matplotlib/icons/black/Forward.png
napari_matplotlib/icons/black/Home.png
napari_matplotlib/icons/black/Pan.png
napari_matplotlib/icons/black/Pan_checked.png
napari_matplotlib/icons/black/Save.png
napari_matplotlib/icons/black/Subplots.png
napari_matplotlib/icons/black/Zoom.png
napari_matplotlib/icons/black/Zoom_checked.png
napari_matplotlib/icons/white/Back.png
napari_matplotlib/icons/white/Customize.png
napari_matplotlib/icons/white/Forward.png
napari_matplotlib/icons/white/Home.png
napari_matplotlib/icons/white/Pan.png
napari_matplotlib/icons/white/Pan_checked.png
napari_matplotlib/icons/white/Save.png
napari_matplotlib/icons/white/Subplots.png
napari_matplotlib/icons/white/Zoom.png
napari_matplotlib/icons/white/Zoom_checked.png
napari_matplotlib/tests/__init__.py
napari_matplotlib/tests/conftest.py
napari_matplotlib/tests/helpers.py
napari_matplotlib/tests/test_histogram.py
napari_matplotlib/tests/test_layer_changes.py
napari_matplotlib/tests/test_slice.py
napari_matplotlib/tests/test_theme.py
napari_matplotlib/tests/test_ui.py
napari_matplotlib/tests/test_util.py
napari_matplotlib/tests/baseline/test_custom_theme.png
napari_matplotlib/tests/baseline/test_feature_histogram.png
napari_matplotlib/tests/baseline/test_feature_histogram_points.png
napari_matplotlib/tests/baseline/test_feature_histogram_vectors.png
napari_matplotlib/tests/baseline/test_histogram_2D.png
napari_matplotlib/tests/baseline/test_histogram_2D_bins.png
napari_matplotlib/tests/baseline/test_histogram_3D.png
napari_matplotlib/tests/baseline/test_no_theme_side_effects.png
napari_matplotlib/tests/baseline/test_slice_2D.png
napari_matplotlib-3.0.1.dist-info/licenses/LICENSE
napari_matplotlib-3.0.1.dist-info/METADATA
napari_matplotlib-3.0.1.dist-info/WHEEL
napari_matplotlib-3.0.1.dist-info/entry_points.txt
napari_matplotlib-3.0.1.dist-info/top_level.txt
napari_matplotlib-3.0.1.dist-info/RECORD
