Metadata-Version: 2.4
Name: napari-matplotlib
Version: 3.0.1
Summary: A plugin to use Matplotlib with napari
Home-page: https://github.com/matplotlib/napari-matplotlib
Author: David Stansby
Author-email: d.stansby@ucl.ac.uk
License: BSD-3-Clause
Project-URL: Bug Tracker, https://github.com/matplotlib/napari-matplotlib/issues
Project-URL: Documentation, https://napari-matplotlib.github.io
Project-URL: Source Code, https://github.com/matplotlib/napari-matplotlib
Project-URL: User Support, https://github.com/matplotlib/napari-matplotlib/issues
Classifier: Development Status :: 5 - Production/Stable
Classifier: Framework :: napari
Classifier: Intended Audience :: Developers
Classifier: License :: OSI Approved :: BSD License
Classifier: Operating System :: OS Independent
Classifier: Programming Language :: Python
Classifier: Programming Language :: Python :: 3
Classifier: Programming Language :: Python :: 3 :: Only
Classifier: Topic :: Software Development :: Testing
Requires-Python: >=3.10
License-File: LICENSE
Requires-Dist: matplotlib
Requires-Dist: napari>=0.5
Requires-Dist: numpy>=1.23
Requires-Dist: tinycss2
Provides-Extra: docs
Requires-Dist: napari[all]; extra == "docs"
Requires-Dist: numpydoc; extra == "docs"
Requires-Dist: pydantic<2; extra == "docs"
Requires-Dist: pydata-sphinx-theme; extra == "docs"
Requires-Dist: sphinx; extra == "docs"
Requires-Dist: sphinx-automodapi; extra == "docs"
Requires-Dist: sphinx-gallery; extra == "docs"
Provides-Extra: testing
Requires-Dist: napari[pyqt6_experimental]>=0.4.18; extra == "testing"
Requires-Dist: pooch; extra == "testing"
Requires-Dist: pyqt6; extra == "testing"
Requires-Dist: pytest; extra == "testing"
Requires-Dist: pytest-cov; extra == "testing"
Requires-Dist: pytest-mock; extra == "testing"
Requires-Dist: pytest-mpl; extra == "testing"
Requires-Dist: pytest-qt; extra == "testing"
Requires-Dist: tox; extra == "testing"
Requires-Dist: pytest-xvfb; sys_platform == "linux" and extra == "testing"
Dynamic: license-file
